test_pkg_sinesh/__init__.py
test_pkg_sinesh-0.1.0.dist-info/METADATA
test_pkg_sinesh-0.1.0.dist-info/WHEEL
test_pkg_sinesh-0.1.0.dist-info/RECORD
