Metadata-Version: 2.1
Name: test-pkg-sinesh
Version: 0.1.0
Summary: 
Author: Test
Author-email: girishvilla@gmail.com
Requires-Python: >=3.12,<4.0
Classifier: Programming Language :: Python :: 3
Classifier: Programming Language :: Python :: 3.12
Requires-Dist: requests (>=2.32.4,<3.0.0)
